vto_frontend/__init__.py
vto_frontend/apps.py
vto_frontend/context_processors.py
vto_frontend/middleware.py
vto_frontend/templates/admin/base.html
vto_frontend/templates/admin/base_site.html
vto_frontend/templates/registration/login.html
vto_frontend/templatetags/markdown_extras.py
vto_frontend-0.0.3.dist-info/METADATA
vto_frontend-0.0.3.dist-info/WHEEL
vto_frontend-0.0.3.dist-info/licenses/LICENSE
vto_frontend-0.0.3.dist-info/RECORD
