Metadata-Version: 2.4
Name: vto-frontend
Version: 0.0.3
Summary: Just a personal test app, not intended for use by anyone else
Project-URL: Repository, https://github.com/venteto/vto-frontend
License-Expression: MIT
License-File: LICENSE
Requires-Python: >=3.13
Requires-Dist: markdown>=3.7
